coposet/__init__.py
coposet/adapters.py
coposet/errors.py
coposet/models/__init__.py
coposet/models/core.py
coposet/models/enrichment.py
coposet/models/posetspace.py
coposet/models/voting.py
coposet/types.py
coposet-0.0.1.dist-info/LICENSE
coposet-0.0.1.dist-info/METADATA
coposet-0.0.1.dist-info/WHEEL
coposet-0.0.1.dist-info/RECORD
