Metadata-Version: 2.3
Name: coposet
Version: 0.0.1
Summary: Collaborative partial orders
Keywords: poset,partial-order,mathematics,codesign,consensus,voting
Author: Deniz Aydin
Author-email: deniz@aydemir.us
Requires-Python: >=3.13,<4.0
Classifier: Development Status :: 3 - Alpha
Classifier: Intended Audience :: Science/Research
Classifier: License :: OSI Approved :: MIT License
Classifier: Programming Language :: Python :: 3
Classifier: Programming Language :: Python :: 3.13
Classifier: Topic :: Scientific/Engineering :: Mathematics
Classifier: Typing :: Typed
Requires-Dist: posets (>=1.0.1,<2.0.0)
Requires-Dist: typing-extensions (>=4.8.0,<5.0.0)
Project-URL: Documentation, https://github.com/daydemir/partial/blob/main/README.md
Project-URL: Homepage, https://github.com/daydemir/partial
Project-URL: Repository, https://github.com/daydemir/partial
